README.md
setup.py
tshine73_utils/__init__.py
tshine73_utils/date_utils.py
tshine73_utils/http_utils.py
tshine73_utils/io_utils.py
tshine73_utils/json_utils.py
tshine73_utils/str_utils.py
tshine73_utils.egg-info/PKG-INFO
tshine73_utils.egg-info/SOURCES.txt
tshine73_utils.egg-info/dependency_links.txt
tshine73_utils.egg-info/requires.txt
tshine73_utils.egg-info/top_level.txt
tshine73_utils/aws/__init__.py
tshine73_utils/aws/redshift_utils.py
tshine73_utils/aws/s3_utils.py
tshine73_utils/aws/secrets_manager_utils.py