Metadata-Version: 2.2
Name: tshine73-utils
Version: 0.2
Summary: tshine73 utils
Author: tshine73
Author-email: fan.steven.chiang@gmail.com
Classifier: Programming Language :: Python :: 3
Classifier: License :: OSI Approved :: MIT License
Classifier: Operating System :: OS Independent
Requires-Python: >=3.12
Requires-Dist: psycopg2-binary==2.9.9
Requires-Dist: boto3==1.36.3
Requires-Dist: requests==2.32.3
Dynamic: author
Dynamic: author-email
Dynamic: classifier
Dynamic: requires-dist
Dynamic: requires-python
Dynamic: summary
